LICENSE
MANIFEST.in
README
requirements.txt
setup.cfg
setup.py
src/anomix/__init__.py
src/anomix.egg-info/PKG-INFO
src/anomix.egg-info/SOURCES.txt
src/anomix.egg-info/dependency_links.txt
src/anomix.egg-info/requires.txt
src/anomix.egg-info/top_level.txt
src/anomix/models/__init__.py
src/anomix/models/base.py
src/anomix/models/models.py
src/anomix/models/utils.py
src/anomix/models/univariate/BetaMixtureModel.py
src/anomix/models/univariate/BinomialMixtureModel.py
src/anomix/models/univariate/CauchyMixtureModel.py
src/anomix/models/univariate/ExponentialMixtureModel.py
src/anomix/models/univariate/GeometricMixtureModel.py
src/anomix/models/univariate/LogNormalMixtureModel.py
src/anomix/models/univariate/NormalMixtureModel.py
src/anomix/models/univariate/PoissonMixtureModel.py
src/anomix/models/univariate/StudentsTMixtureModel.py
src/anomix/models/univariate/ZeroInflatedBinomialMixtureModel.py
src/anomix/models/univariate/ZeroInflatedExponentialMixtureModel.py
src/anomix/models/univariate/ZeroInflatedNormalMixtureModel.py
src/anomix/models/univariate/ZeroInflatedPoissonMixtureModel.py
src/anomix/models/univariate/ZetaMixtureModel.py
src/anomix/models/univariate/__init__.py
src/anomix/utils/__init__.py
src/anomix/utils/exceptions.py
src/anomix/utils/static.py
src/anomix/utils/utils.py