Metadata-Version: 2.1
Name: anomix
Version: 0.2.7
Summary: Mixture Models for anomaly detection
Home-page: https://github.com/TRSS-Research/anomix
Author: andrew Follmann
Author-email: follmann.andrew@gmail.com
License: UNKNOWN
Platform: UNKNOWN
Classifier: Programming Language :: Python :: 3
Classifier: Topic :: Scientific/Engineering
Classifier: Development Status :: 4 - Beta
Classifier: Operating System :: OS Independent
Classifier: Intended Audience :: End Users/Desktop
Classifier: Intended Audience :: Developers
Classifier: Intended Audience :: Science/Research
Requires-Python: >=3.6
